Combinational/encoder_8to3/encoder.v
module encoder(
input [7:0] a,
output reg [2:0] y);
always@(*)
begin
case(a)
8'b10000000:y=3'b000;
8'b01000000:y=3'b001;
8'b00100000:y=3'b010;
8'b00010000:y=3'b011;
8'b00001000:y=3'b100;
8'b00000100:y=3'b101;
8'b00000010:y=3'b110;
8'b00000001:y=3'b111;
default:y=3'b000;
endcase
end
endmodule

Combinational/encoder_8to3/encoder_tb.v
module encoder_tb;
reg [7:0] a;
wire [2:0] y;
encoder uut(
.a(a),
.y(y));
initial begin
$dumpfile("wave.vcd");
$dumpvars(0 ,encoder_tb);
$monitor("time=%0t a=%b y=%b",$time,a,y);
a=8'b10000000;#6;
a=8'b01000000;#6;
a=8'b00100000;#6;
a=8'b00010000;#6;
a=8'b00001000;#6;
a=8'b00000100;#6;
a=8'b00000010;#6;
a=8'b00000001;#6;
$finish;
end
endmodule

Combinational/encoder_8to3/wave.vcd
$date
	Sun Jun 21 13:39:06 2026
$end
$version
	Icarus Verilog
$end
$timescale
	1s
$end
$scope module encoder_tb $end
$var wire 3 ! y [2:0] $end
$var reg 8 " a [7:0] $end
$scope module uut $end
$var wire 8 # a [7:0] $end
$var reg 3 $ y [2:0] $end
$upscope $end
$upscope $end
$enddefinitions $end
#0
$dumpvars
b0 $
b10000000 #
b10000000 "
b0 !
$end
#6
b1 !
b1 $
b1000000 "
b1000000 #
#12
b10 !
b10 $
b100000 "
b100000 #
#18
b11 !
b11 $
b10000 "
b10000 #
#24
b100 !
b100 $
b1000 "
b1000 #
#30
b101 !
b101 $
b100 "
b100 #
#36
b110 !
b110 $
b10 "
b10 #
#42
b111 !
b111 $
b1 "
b1 #
