Combinational/comparator/comparator.v
module comparator(
input a,
input b,
output EQ,
output GT,
output LT
);
assign EQ=(a^~b);
assign GT=(a&~b);
assign LT=(~a&b);
endmodule

Combinational/comparator/comparator_4.v
module comparator_4(
input [3:0] a,
input [3:0] b,
output EQ,
output GT,
output LT
);
wire eq0,eq1,eq2,eq3,gt0,gt1,gt2,gt3,lt0,lt1,lt2,lt3;
comparator co0(
.a(a[0]),
.b(b[0]),
.EQ(eq0),
.GT(gt0),
.LT(lt0));
comparator co1(
.a(a[1]),
.b(b[1]),
.EQ(eq1),
.GT(gt1),
.LT(lt1));
comparator co2(
.a(a[2]),
.b(b[2]),
.EQ(eq2),
.GT(gt2),
.LT(lt2));
comparator co3(
.a(a[3]),
.b(b[3]),
.EQ(eq3),
.GT(gt3),
.LT(lt3));
assign EQ= (eq0&eq1&eq2&eq3);
assign GT= (gt3|(eq3&gt2)|(eq3&eq2&gt1)|(eq3&eq2&eq1&gt0));
assign LT= (lt3|(eq3&lt2)|(eq3&eq2&lt1)|(eq3&eq2&eq1&lt0));
endmodule

Combinational/comparator/comparator_4_tb.v
module comparator_4_tb;
reg [3:0] a;
reg [3:0] b;
wire EQ;
wire GT;
wire LT;
comparator_4 uut(
.a(a),
.b(b),
.EQ(EQ),
.GT(GT),
.LT(LT));
initial begin
$dumpfile("wave.vcd");
$dumpvars(0,comparator_4_tb);
$monitor("time=%0t a=%b b=%b EQ=%b GT=%b LT=%b",$time,a,b,EQ,GT,LT);
{a,b}=8'b0000_0000;#3;
{a,b}=8'b0001_0000;#3;
{a,b}=8'b0000_0001;#3;
{a,b}=8'b1010_1001;#3;
{a,b}=8'b0110_1001;#3;
{a,b}=8'b1111_1111;#3;
{a,b}=8'b1000_0111;#3;
{a,b}=8'b0111_1000;#3;
$finish;
end
endmodule

Combinational/comparator/wave.vcd
$date
	Thu Jul  2 16:01:56 2026
$end
$version
	Icarus Verilog
$end
$timescale
	1s
$end
$scope module comparator_4_tb $end
$var wire 1 ! LT $end
$var wire 1 " GT $end
$var wire 1 # EQ $end
$var reg 4 $ a [3:0] $end
$var reg 4 % b [3:0] $end
$scope module uut $end
$var wire 1 # EQ $end
$var wire 1 " GT $end
$var wire 1 ! LT $end
$var wire 4 & a [3:0] $end
$var wire 4 ' b [3:0] $end
$var wire 1 ( lt3 $end
$var wire 1 ) lt2 $end
$var wire 1 * lt1 $end
$var wire 1 + lt0 $end
$var wire 1 , gt3 $end
$var wire 1 - gt2 $end
$var wire 1 . gt1 $end
$var wire 1 / gt0 $end
$var wire 1 0 eq3 $end
$var wire 1 1 eq2 $end
$var wire 1 2 eq1 $end
$var wire 1 3 eq0 $end
$scope module co0 $end
$var wire 1 3 EQ $end
$var wire 1 / GT $end
$var wire 1 + LT $end
$var wire 1 4 a $end
$var wire 1 5 b $end
$upscope $end
$scope module co1 $end
$var wire 1 2 EQ $end
$var wire 1 . GT $end
$var wire 1 * LT $end
$var wire 1 6 a $end
$var wire 1 7 b $end
$upscope $end
$scope module co2 $end
$var wire 1 1 EQ $end
$var wire 1 - GT $end
$var wire 1 ) LT $end
$var wire 1 8 a $end
$var wire 1 9 b $end
$upscope $end
$scope module co3 $end
$var wire 1 0 EQ $end
$var wire 1 , GT $end
$var wire 1 ( LT $end
$var wire 1 : a $end
$var wire 1 ; b $end
$upscope $end
$upscope $end
$upscope $end
$enddefinitions $end
#0
$dumpvars
0;
0:
09
08
07
06
05
04
13
12
11
10
0/
0.
0-
0,
0+
0*
0)
0(
b0 '
b0 &
b0 %
b0 $
1#
0"
0!
$end
#3
0#
1"
03
1/
14
b1 $
b1 &
#6
1!
0"
1+
0/
04
15
b0 $
b0 &
b1 %
b1 '
#9
0!
1"
02
1.
0(
16
1:
1;
b1010 $
b1010 &
b1001 %
b1001 '
#12
0"
1!
1(
01
1-
00
18
0:
b110 $
b110 &
#15
0!
1#
0+
0(
0.
0-
13
10
12
11
14
1:
17
19
b1111 $
b1111 &
b1111 %
b1111 '
#18
1"
1+
1*
1)
0#
1,
03
02
01
00
04
06
08
0;
b1000 $
b1000 &
b111 %
b111 '
#21
1!
0"
1(
1/
1.
1-
0,
0+
0*
0)
14
16
18
0:
05
07
09
1;
b111 $
b111 &
b1000 %
b1000 '
