Sequential/dff_rst_syn/dff_rst.v
module dff_rst(
input d,
input clk,
input rst,
output reg q);
always@(posedge clk)
begin
if(rst)
q=0;
else
q<=d;
end
endmodule

Sequential/dff_rst_syn/dff_rst_tb.v
module dff_rst_tb;
reg d;
reg clk;
reg rst;
wire q;
dff_rst uut(
.d(d),
.clk(clk),
.rst(rst),
.q(q));
initial begin
clk=0;
forever #5 clk=~clk;
end
initial begin
$dumpfile("wave.vcd");
$dumpvars(0, dff_rst_tb);
$monitor("time=%0t d=%b clk=%b rst=%b q=%b",$time,d,clk,rst,q);
rst=1;d=1;#5;
rst=0;d=0;#6;
d=1;#6;
d=0;#6;
rst=1;#6;
rst=0;d=1;#5;
$finish;
end
endmodule

Sequential/dff_rst_syn/wave.vcd
$date
	Sun Jun 21 11:42:19 2026
$end
$version
	Icarus Verilog
$end
$timescale
	1s
$end
$scope module dff_rst_tb $end
$var wire 1 ! q $end
$var reg 1 " clk $end
$var reg 1 # d $end
$var reg 1 $ rst $end
$scope module uut $end
$var wire 1 " clk $end
$var wire 1 # d $end
$var wire 1 $ rst $end
$var reg 1 ! q $end
$upscope $end
$upscope $end
$enddefinitions $end
#0
$dumpvars
1$
1#
0"
x!
$end
#5
0!
0#
0$
1"
#10
0"
#11
1#
#15
1!
1"
#17
0#
#20
0"
#23
1$
#25
0!
1"
#29
1#
0$
