Combinational/carry_adder/carry_adder.v
module carry_adder(
input [3:0] a,
input [3:0] b,
output [3:0] s,
input cin,
output c5);
wire p1,p2,p3,p4;
wire g1,g2,g3,g4;
wire c1,c2,c3,c4;
assign c1=cin;
assign g1=a[0]&b[0];
assign g2=a[1]&b[1];
assign g3=a[2]&b[2];
assign g4=a[3]&b[3];
assign p1=a[0]^b[0];
assign p2=a[1]^b[1];
assign p3=a[2]^b[2];
assign p4=a[3]^b[3];
assign s[0]=p1^c1;
assign s[1]=p2^c2;
assign s[2]=p3^c3;
assign s[3]=p4^c4;
assign c2=g1|(p1&c1);
assign c3=g2|(g1&p2)|(p2&p1&c1);
assign c4=g3|(g2&p3)|(g1&p2&p3)|(p3&p2&p1&c1);
assign c5=g4|(g3&p4)|(g2&p3&p4)|(g1&p2&p3&p4)|(p4&p3&p2&p1&c1);
endmodule

Combinational/carry_adder/carry_adder_tb.v
module carry_adder_tb;
reg [3:0] a;
reg [3:0] b;
wire [3:0] s;
reg cin;
wire cout;
carry_adder uut(
.a(a),
.b(b),
.s(s),
.cin(cin),
.c5(cout));
initial begin
$dumpfile("wave.vcd");
$dumpvars(0,carry_adder_tb);
$monitor("time=%0t a=%b b=%b cin=%b s=%b cout=%b",$time,a,b,cin,s,cout);
cin=1'b0;
{a,b}=8'b0000_0000;#3;
{a,b}=8'b0001_0001;#3;
{a,b}=8'b0010_0010;#3;
{a,b}=8'b0011_0011;#3;
{a,b}=8'b0100_0100;#3;
{a,b}=8'b0101_0101;#3;
{a,b}=8'b0110_0110;#3;
{a,b}=8'b0111_0111;#3;
{a,b}=8'b1000_1000;#3;
{a,b}=8'b1001_1001;#3;
{a,b}=8'b1010_1010;#3;
{a,b}=8'b1011_1011;#3;
{a,b}=8'b1100_1100;#3;
{a,b}=8'b1101_1101;#3;
{a,b}=8'b1110_1110;#3;
{a,b}=8'b1111_1111;#3;
cin=1'b1;
{a,b}=8'b0000_0000;#3;
{a,b}=8'b0001_0001;#3;
{a,b}=8'b0010_0010;#3;
{a,b}=8'b0011_0011;#3;
{a,b}=8'b0100_0100;#3;
{a,b}=8'b0101_0101;#3;
{a,b}=8'b0110_0110;#3;
{a,b}=8'b0111_0111;#3;
{a,b}=8'b1000_1000;#3;
{a,b}=8'b1001_1001;#3;
{a,b}=8'b1010_1010;#3;
{a,b}=8'b1011_1011;#3;
{a,b}=8'b1100_1100;#3;
{a,b}=8'b1101_1101;#3;
{a,b}=8'b1110_1110;#3;
{a,b}=8'b1111_1111;#3;
$finish;
end
endmodule

Combinational/carry_adder/wave.vcd
$date
	Fri Jul  3 20:58:59 2026
$end
$version
	Icarus Verilog
$end
$timescale
	1s
$end
$scope module carry_adder_tb $end
$var wire 4 ! s [3:0] $end
$var wire 1 " cout $end
$var reg 4 # a [3:0] $end
$var reg 4 $ b [3:0] $end
$var reg 1 % cin $end
$scope module uut $end
$var wire 4 & a [3:0] $end
$var wire 4 ' b [3:0] $end
$var wire 1 ( c1 $end
$var wire 1 ) c2 $end
$var wire 1 * c3 $end
$var wire 1 + c4 $end
$var wire 1 " c5 $end
$var wire 1 % cin $end
$var wire 1 , g1 $end
$var wire 1 - g2 $end
$var wire 1 . g3 $end
$var wire 1 / g4 $end
$var wire 1 0 p1 $end
$var wire 1 1 p2 $end
$var wire 1 2 p3 $end
$var wire 1 3 p4 $end
$var wire 4 4 s [3:0] $end
$upscope $end
$upscope $end
$enddefinitions $end
#0
$dumpvars
b0 4
03
02
01
00
0/
0.
0-
0,
0+
0*
0)
0(
b0 '
b0 &
0%
b0 $
b0 #
0"
b0 !
$end
#3
b10 !
b10 4
1)
1,
b1 #
b1 &
b1 $
b1 '
#6
b100 !
b100 4
1*
0)
0,
1-
b10 #
b10 &
b10 $
b10 '
#9
b110 !
b110 4
1)
1,
b11 #
b11 &
b11 $
b11 '
#12
1+
b1000 !
b1000 4
0*
0)
0,
0-
1.
b100 #
b100 &
b100 $
b100 '
#15
b1010 !
b1010 4
1)
1,
b101 #
b101 &
b101 $
b101 '
#18
b1100 !
b1100 4
1*
0)
0,
1-
b110 #
b110 &
b110 $
b110 '
#21
b1110 !
b1110 4
1)
1,
b111 #
b111 &
b111 $
b111 '
#24
1"
0+
b0 !
b0 4
0*
0)
0,
0-
0.
1/
b1000 #
b1000 &
b1000 $
b1000 '
#27
b10 !
b10 4
1)
1,
b1001 #
b1001 &
b1001 $
b1001 '
#30
b100 !
b100 4
1*
0)
0,
1-
b1010 #
b1010 &
b1010 $
b1010 '
#33
b110 !
b110 4
1)
1,
b1011 #
b1011 &
b1011 $
b1011 '
#36
1+
b1000 !
b1000 4
0*
0)
0,
0-
1.
b1100 #
b1100 &
b1100 $
b1100 '
#39
b1010 !
b1010 4
1)
1,
b1101 #
b1101 &
b1101 $
b1101 '
#42
b1100 !
b1100 4
1*
0)
0,
1-
b1110 #
b1110 &
b1110 $
b1110 '
#45
b1110 !
b1110 4
1)
1,
b1111 #
b1111 &
b1111 $
b1111 '
#48
0"
0+
0*
0)
0,
0-
0.
0/
b1 !
b1 4
b0 #
b0 &
b0 $
b0 '
1(
1%
#51
b11 !
b11 4
1)
1,
b1 #
b1 &
b1 $
b1 '
#54
b101 !
b101 4
1*
0)
0,
1-
b10 #
b10 &
b10 $
b10 '
#57
b111 !
b111 4
1)
1,
b11 #
b11 &
b11 $
b11 '
#60
1+
b1001 !
b1001 4
0*
0)
0,
0-
1.
b100 #
b100 &
b100 $
b100 '
#63
b1011 !
b1011 4
1)
1,
b101 #
b101 &
b101 $
b101 '
#66
b1101 !
b1101 4
1*
0)
0,
1-
b110 #
b110 &
b110 $
b110 '
#69
b1111 !
b1111 4
1)
1,
b111 #
b111 &
b111 $
b111 '
#72
1"
0+
b1 !
b1 4
0*
0)
0,
0-
0.
1/
b1000 #
b1000 &
b1000 $
b1000 '
#75
b11 !
b11 4
1)
1,
b1001 #
b1001 &
b1001 $
b1001 '
#78
b101 !
b101 4
1*
0)
0,
1-
b1010 #
b1010 &
b1010 $
b1010 '
#81
b111 !
b111 4
1)
1,
b1011 #
b1011 &
b1011 $
b1011 '
#84
1+
b1001 !
b1001 4
0*
0)
0,
0-
1.
b1100 #
b1100 &
b1100 $
b1100 '
#87
b1011 !
b1011 4
1)
1,
b1101 #
b1101 &
b1101 $
b1101 '
#90
b1101 !
b1101 4
1*
0)
0,
1-
b1110 #
b1110 &
b1110 $
b1110 '
#93
b1111 !
b1111 4
1)
1,
b1111 #
b1111 &
b1111 $
b1111 '
