Combinational/mux4_1/mux4_1.v
module mux4_1(
input [3:0] a,
input [1:0] sel,
output reg y);
always@(*)
begin
case(sel)
2'b00:y=a[0];
2'b01:y=a[1];
2'b10:y=a[2];
2'b11:y=a[3];
default:y=4'b0000;
endcase
end
endmodule

Combinational/mux4_1/mux4_1tb.v
module mux4_1tb;
reg [3:0] a;
reg [1:0] sel;
wire y;
mux4_1 uut(.a(a),.sel(sel),.y(y));
initial begin
$dumpfile("wave.vcd");
$dumpvars(0, mux4_1tb);
$monitor("time=%0t a=%b sel=%b y=%b",$time,a,sel,y);
a=4'b1111;
sel=2'b00;#3;
sel=2'b01;#3;
sel=2'b10;#3;
sel=2'b11;#3;
a=4'b0000;
sel=2'b00;#3;
sel=2'b01;#3;
sel=2'b10;#3;
sel=2'b11;#3;
$finish;
end
endmodule

Combinational/mux4_1/wave.vcd
$date
	Sat Jun 27 23:52:28 2026
$end
$version
	Icarus Verilog
$end
$timescale
	1s
$end
$scope module mux4_1tb $end
$var wire 1 ! y $end
$var reg 4 " a [3:0] $end
$var reg 2 # sel [1:0] $end
$scope module uut $end
$var wire 4 $ a [3:0] $end
$var wire 2 % sel [1:0] $end
$var reg 1 ! y $end
$upscope $end
$upscope $end
$enddefinitions $end
#0
$dumpvars
b0 %
b1111 $
b0 #
b1111 "
1!
$end
#3
b1 #
b1 %
#6
b10 #
b10 %
#9
b11 #
b11 %
#12
0!
b0 #
b0 %
b0 "
b0 $
#15
b1 #
b1 %
#18
b10 #
b10 %
#21
b11 #
b11 %
