Combinational/decoder_3to8/decoder.v
module decoder(
input [2:0] a,
output reg [7:0] y);
always@(*)
begin
case(a)
3'b000:y=8'b00000001;
3'b001:y=8'b00000010;
3'b010:y=8'b00000100;
3'b011:y=8'b00001000;
3'b100:y=8'b00010000;
3'b101:y=8'b00100000;
3'b110:y=8'b01000000;
3'b111:y=8'b10000000;
default:y=8'b00000000;
endcase
end
endmodule

Combinational/decoder_3to8/decoder_tb.v
module decoder_tb;
reg [2:0] a;
wire [7:0] y;
decoder uut(
.a(a),
.y(y));
initial begin
$dumpfile("wave.vcd");
$dumpvars(0 ,decoder_tb);
$monitor("time=%0t a=%b y=%b",$time,a,y);
a=3'b000;#6;
a=3'b001;#6;
a=3'b010;#6;
a=3'b011;#6;
a=3'b100;#6;
a=3'b101;#6;
a=3'b110;#6;
a=3'b111;#6;
$finish;
end
endmodule

Combinational/decoder_3to8/wave.vcd
$date
	Sun Jun 21 13:19:26 2026
$end
$version
	Icarus Verilog
$end
$timescale
	1s
$end
$scope module decoder_tb $end
$var wire 8 ! y [7:0] $end
$var reg 3 " a [2:0] $end
$scope module uut $end
$var wire 3 # a [2:0] $end
$var reg 8 $ y [7:0] $end
$upscope $end
$upscope $end
$enddefinitions $end
#0
$dumpvars
b1 $
b0 #
b0 "
b1 !
$end
#6
b10 !
b10 $
b1 "
b1 #
#12
b100 !
b100 $
b10 "
b10 #
#18
b1000 !
b1000 $
b11 "
b11 #
#24
b10000 !
b10000 $
b100 "
b100 #
#30
b100000 !
b100000 $
b101 "
b101 #
#36
b1000000 !
b1000000 $
b110 "
b110 #
#42
b10000000 !
b10000000 $
b111 "
b111 #
