Sequential/register_ena/reg_ena.v
module reg_ena(
input [3:0] d,
input clk,
input ena,
output reg [3:0] q);
always@(posedge clk)
begin
if(ena)
q<=d;
else
q<=d;
end
endmodule

Sequential/register_ena/reg_ena_tb.v
module reg_ena_tb;
reg [3:0] d;
reg clk;
reg ena;
wire [3:0] q;
reg_ena uut(
.d(d),
.clk(clk),
.ena(ena),
.q(q));
initial begin
clk=0;
forever #5 clk=~clk;
end
initial begin
$monitor("time=%0t d=%b clk=%b ena=%b q=%b",$time,d,clk,ena,q);
$dumpfile("wave.vcd");
$dumpvars(0, reg_ena_tb);
ena=0;d=4'b0000;#3;
ena=1;d=4'b1010;#8;
d=4'b1111;#8;
ena=0;d=4'b1111;#5;
ena=1;d=4'b0001;#5;
$finish;
end
endmodule

Sequential/register_ena/wave.vcd
$date
	Sun Jun 21 12:33:25 2026
$end
$version
	Icarus Verilog
$end
$timescale
	1s
$end
$scope module reg_ena_tb $end
$var wire 4 ! q [3:0] $end
$var reg 1 " clk $end
$var reg 4 # d [3:0] $end
$var reg 1 $ ena $end
$scope module uut $end
$var wire 1 " clk $end
$var wire 4 % d [3:0] $end
$var wire 1 $ ena $end
$var reg 4 & q [3:0] $end
$upscope $end
$upscope $end
$enddefinitions $end
#0
$dumpvars
bx &
b0 %
0$
b0 #
0"
bx !
$end
#3
b1010 #
b1010 %
1$
#5
b1010 !
b1010 &
1"
#10
0"
#11
b1111 #
b1111 %
#15
b1111 !
b1111 &
1"
#19
0$
#20
0"
#24
b1 #
b1 %
1$
#25
b1 !
b1 &
1"
