Combinational/demux/demux.v
module demux(
input d,
input [1:0] sel,
output reg [3:0] y);
always@(*)
begin
case(sel)
2'b00:y[0]=d;
2'b01:y[1]=d;
2'b10:y[2]=d;
2'b11:y[3]=d;
endcase
end
endmodule

Combinational/demux/demux_tb.v
module demux_tb;
reg d;
reg [1:0] sel;
wire [3:0] y;
demux uut(
.d(d),
.sel(sel),
.y(y));
initial begin
$dumpfile("wave.vcd");
$dumpvars(0, demux_tb);
$monitor("time=%0t d=%b sel=%b y=%b",$time,d,sel,y);
d=1;
sel=2'b00;#5;
sel=2'b01;#5;
sel=2'b10;#5;
sel=2'b11;#5;
d=0;
sel=2'b00;#5;
sel=2'b01;#5;
sel=2'b10;#5;
sel=2'b11;#5;
$finish;
end
endmodule

Combinational/demux/wave.vcd
$date
	Thu Jul  2 15:42:16 2026
$end
$version
	Icarus Verilog
$end
$timescale
	1s
$end
$scope module demux_tb $end
$var wire 4 ! y [3:0] $end
$var reg 1 " d $end
$var reg 2 # sel [1:0] $end
$scope module uut $end
$var wire 1 " d $end
$var wire 2 $ sel [1:0] $end
$var reg 4 % y [3:0] $end
$upscope $end
$upscope $end
$enddefinitions $end
#0
$dumpvars
bx1 %
b0 $
b0 #
1"
bx1 !
$end
#5
bx11 !
bx11 %
b1 #
b1 $
#10
bx111 !
bx111 %
b10 #
b10 $
#15
b1111 !
b1111 %
b11 #
b11 $
#20
b1110 !
b1110 %
b0 #
b0 $
0"
#25
b1100 !
b1100 %
b1 #
b1 $
#30
b1000 !
b1000 %
b10 #
b10 $
#35
b0 !
b0 %
b11 #
b11 $
