Combinational/ripple_adder/full_adder.v
module full_adder(
input a,
input b,
input cin,
output s,
output cout);
assign s=a^b^cin;
assign cout=(a&b)|(a&cin)|(b&cin);
endmodule

Combinational/ripple_adder/ripple_carry_adder.v
module ripple_carry_adder(
input [3:0] a,
input [3:0] b,
output cout,
output [3:0] s );
wire c0,c1,c2;
full_adder fa1 (
.a(a[0]),
.b(b[0]),
.cout(c0),
.cin(1'b0),
.s(s[0]));
full_adder fa2 (
.a(a[1]),
.b(b[1]),
.cout(c1),
.cin(c0),
.s(s[1]));
full_adder fa3 (
.a(a[2]),
.b(b[2]),
.cout(c2),
.cin(c1),
.s(s[2]));
full_adder fa4 (
.a(a[3]),
.b(b[3]),
.cout(cout),
.cin(c2),
.s(s[3]));
endmodule

Combinational/ripple_adder/ripple_tb.v
module ripple_tb;
reg [3:0] a;
reg [3:0] b;
wire [3:0] s;
wire cout;
ripple_carry_adder uut (
.a(a),
.b(b),
.s(s),
.cout(cout));
initial begin
$dumpfile("wave.vcd");
$dumpvars(0,ripple_tb);
$monitor("time=%0t a=%b b=%b s=%b cout=%b",$time,a,b,s,cout);
{a,b}=8'b0000_0000;#3;
{a,b}=8'b0001_0001;#3;
{a,b}=8'b0010_0010;#3;
{a,b}=8'b0011_0011;#3;
{a,b}=8'b0100_0100;#3;
{a,b}=8'b0101_0101;#3;
{a,b}=8'b0110_0110;#3;
{a,b}=8'b0111_0111;#3;
{a,b}=8'b1000_1000;#3;
{a,b}=8'b1001_1001;#3;
{a,b}=8'b1010_1010;#3;
{a,b}=8'b1011_1011;#3;
{a,b}=8'b1100_1100;#3;
{a,b}=8'b1101_1101;#3;
{a,b}=8'b1110_1110;#3;
{a,b}=8'b1111_1111;#3;
$finish;
end
endmodule

Combinational/ripple_adder/wave.vcd
$date
	Fri Jul  3 14:27:52 2026
$end
$version
	Icarus Verilog
$end
$timescale
	1s
$end
$scope module ripple_tb $end
$var wire 4 ! s [3:0] $end
$var wire 1 " cout $end
$var reg 4 # a [3:0] $end
$var reg 4 $ b [3:0] $end
$scope module uut $end
$var wire 4 % a [3:0] $end
$var wire 4 & b [3:0] $end
$var wire 4 ' s [3:0] $end
$var wire 1 " cout $end
$var wire 1 ( c2 $end
$var wire 1 ) c1 $end
$var wire 1 * c0 $end
$scope module fa1 $end
$var wire 1 + a $end
$var wire 1 , b $end
$var wire 1 - cin $end
$var wire 1 * cout $end
$var wire 1 . s $end
$upscope $end
$scope module fa2 $end
$var wire 1 / a $end
$var wire 1 0 b $end
$var wire 1 * cin $end
$var wire 1 ) cout $end
$var wire 1 1 s $end
$upscope $end
$scope module fa3 $end
$var wire 1 2 a $end
$var wire 1 3 b $end
$var wire 1 ) cin $end
$var wire 1 ( cout $end
$var wire 1 4 s $end
$upscope $end
$scope module fa4 $end
$var wire 1 5 a $end
$var wire 1 6 b $end
$var wire 1 ( cin $end
$var wire 1 " cout $end
$var wire 1 7 s $end
$upscope $end
$upscope $end
$upscope $end
$enddefinitions $end
#0
$dumpvars
07
06
05
04
03
02
01
00
0/
0.
0-
0,
0+
0*
0)
0(
b0 '
b0 &
b0 %
b0 $
b0 #
0"
b0 !
$end
#3
b10 !
b10 '
11
1*
1+
1,
b1 #
b1 %
b1 $
b1 &
#6
01
0*
b100 !
b100 '
14
1)
0+
1/
0,
10
b10 #
b10 %
b10 $
b10 &
#9
b110 !
b110 '
11
1*
1+
1,
b11 #
b11 %
b11 $
b11 &
#12
01
04
0*
0)
b1000 !
b1000 '
17
1(
0+
0/
12
0,
00
13
b100 #
b100 %
b100 $
b100 &
#15
b1010 !
b1010 '
11
1*
1+
1,
b101 #
b101 %
b101 $
b101 &
#18
01
0*
b1100 !
b1100 '
14
1)
0+
1/
0,
10
b110 #
b110 %
b110 $
b110 &
#21
b1110 !
b1110 '
11
1*
1+
1,
b111 #
b111 %
b111 $
b111 &
#24
01
04
b0 !
b0 '
07
0*
0)
0(
1"
0+
0/
02
15
0,
00
03
16
b1000 #
b1000 %
b1000 $
b1000 &
#27
b10 !
b10 '
11
1*
1+
1,
b1001 #
b1001 %
b1001 $
b1001 &
#30
01
0*
b100 !
b100 '
14
1)
0+
1/
0,
10
b1010 #
b1010 %
b1010 $
b1010 &
#33
b110 !
b110 '
11
1*
1+
1,
b1011 #
b1011 %
b1011 $
b1011 &
#36
01
04
0*
0)
b1000 !
b1000 '
17
1(
0+
0/
12
0,
00
13
b1100 #
b1100 %
b1100 $
b1100 &
#39
b1010 !
b1010 '
11
1*
1+
1,
b1101 #
b1101 %
b1101 $
b1101 &
#42
01
0*
b1100 !
b1100 '
14
1)
0+
1/
0,
10
b1110 #
b1110 %
b1110 $
b1110 &
#45
b1110 !
b1110 '
11
1*
1+
1,
b1111 #
b1111 %
b1111 $
b1111 &
