Combinational/up_counter/up_count.v
module up_count(
input clk,
input rst,
output reg [3:0] q); 
always@(posedge clk)
begin
if(rst)
q<=4'b0000;
else
q<=q+1;
end
endmodule

Combinational/up_counter/up_count_tb.v
module up_count_tb;
reg clk;
reg rst;
wire [3:0] q;
up_count uut(
.clk(clk),
.rst(rst),
.q(q));
initial begin
clk=0;
forever #5 clk=~clk;
end
initial begin
$dumpfile("wave.vcd");
$dumpvars(0, up_count_tb);
$monitor("$time=%0t clk=%b rst=%b q=%b",$time,clk,rst,q);
rst=1;#8;
rst=0;#100;
rst=1;#5;
rst=0;#20;
$finish;
end
endmodule

Combinational/up_counter/wave.vcd
$date
	Sun Jun 21 12:49:12 2026
$end
$version
	Icarus Verilog
$end
$timescale
	1s
$end
$scope module up_count_tb $end
$var wire 4 ! q [3:0] $end
$var reg 1 " clk $end
$var reg 1 # rst $end
$scope module uut $end
$var wire 1 " clk $end
$var wire 1 # rst $end
$var reg 4 $ q [3:0] $end
$upscope $end
$upscope $end
$enddefinitions $end
#0
$dumpvars
bx $
1#
0"
bx !
$end
#5
b0 !
b0 $
1"
#8
0#
#10
0"
#15
b1 !
b1 $
1"
#20
0"
#25
b10 !
b10 $
1"
#30
0"
#35
b11 !
b11 $
1"
#40
0"
#45
b100 !
b100 $
1"
#50
0"
#55
b101 !
b101 $
1"
#60
0"
#65
b110 !
b110 $
1"
#70
0"
#75
b111 !
b111 $
1"
#80
0"
#85
b1000 !
b1000 $
1"
#90
0"
#95
b1001 !
b1001 $
1"
#100
0"
#105
b1010 !
b1010 $
1"
#108
1#
#110
0"
#113
0#
#115
b1011 !
b1011 $
1"
#120
0"
#125
b1100 !
b1100 $
1"
