Combinational/carry skip adder/full_adder.v
module full_adder(
input a,
input b,
input cin,
output sum,
output cout);
assign sum=a^b^cin;
assign cout=(a&b)|(a&cin)|(b&cin);
endmodule

Combinational/carry skip adder/rca.v
module rca(
input [3:0] a,
input [3:0] b,
input cin,
output [3:0] sum,
output cout);
wire c1,c2,c3;
full_adder fa0 (
.a(a[0]),
.b(b[0]),
.cin(cin),
.sum(sum[0]),
.cout(c1));
full_adder fa1 (
.a(a[1]),
.b(b[1]),
.cin(c1),
.sum(sum[1]),
.cout(c2));
full_adder fa2 (
.a(a[2]),
.b(b[2]),
.cin(c1),
.sum(sum[2]),
.cout(c3));
full_adder fa3 (
.a(a[3]),
.b(b[3]),
.cin(c2),
.sum(sum[3]),
.cout(cout));
endmodule

Combinational/carry skip adder/carry_skip_adder.v
module carry_skip_adder(
input [3:0] a,
input [3:0] b,
input cin,
output [3:0] sum,
output cout);
wire c4;
wire [3:0] p;
wire bp;
rca rca0 (
.a(a),
.b(b),
.cin(cin),
.sum(sum),
.cout(c4));
assign p=a^b;
assign bp= &p;
assign cout = bp ? cin : c4 ;
endmodule

Combinational/carry skip adder/csa_tb.v
module csa_tb;
reg [3:0] a;
reg [3:0] b;
reg cin;
wire [3:0] sum;
wire cout;
carry_skip_adder uut(
.a(a),
.b(b),
.cin(cin),
.sum(sum),
.cout(cout));
initial begin
$dumpfile("wave.vcd");
$dumpvars(0,csa_tb);
$monitor("time=%0t a=%b b=%b cin=%b sum=%b cout=%b",$time,a,b,cin,sum,cout);
    cin=1'b0;
    a = 4'b0000; b = 4'b0000; #10;
    a = 4'b0001; b = 4'b0001; #10;
    a = 4'b0010; b = 4'b0011; #10;
    a = 4'b0101; b = 4'b0011; #10;
    a = 4'b0111; b = 4'b0001; #10;
    a = 4'b1111; b = 4'b0001; #10;
    a = 4'b1111; b = 4'b1111; #10;
    cin=1'b1;
    a = 4'b0000; b = 4'b0000; #10;
    a = 4'b0001; b = 4'b0001; #10;
    a = 4'b0010; b = 4'b0011; #10;
    a = 4'b0101; b = 4'b0011; #10;
    a = 4'b0111; b = 4'b0001; #10;
    a = 4'b1111; b = 4'b0001; #10;
    a = 4'b1111; b = 4'b1111; #10;
$finish;
end
endmodule

Combinational/carry skip adder/wave.vcd
$date
	Tue Jul 14 21:05:24 2026
$end
$version
	Icarus Verilog
$end
$timescale
	1s
$end
$scope module csa_tb $end
$var wire 4 ! sum [3:0] $end
$var wire 1 " cout $end
$var reg 4 # a [3:0] $end
$var reg 4 $ b [3:0] $end
$var reg 1 % cin $end
$scope module uut $end
$var wire 4 & a [3:0] $end
$var wire 4 ' b [3:0] $end
$var wire 1 % cin $end
$var wire 4 ( p [3:0] $end
$var wire 4 ) sum [3:0] $end
$var wire 1 " cout $end
$var wire 1 * c4 $end
$var wire 1 + bp $end
$scope module rca0 $end
$var wire 4 , a [3:0] $end
$var wire 4 - b [3:0] $end
$var wire 1 % cin $end
$var wire 4 . sum [3:0] $end
$var wire 1 * cout $end
$var wire 1 / c3 $end
$var wire 1 0 c2 $end
$var wire 1 1 c1 $end
$scope module fa0 $end
$var wire 1 2 a $end
$var wire 1 3 b $end
$var wire 1 % cin $end
$var wire 1 1 cout $end
$var wire 1 4 sum $end
$upscope $end
$scope module fa1 $end
$var wire 1 5 a $end
$var wire 1 6 b $end
$var wire 1 1 cin $end
$var wire 1 0 cout $end
$var wire 1 7 sum $end
$upscope $end
$scope module fa2 $end
$var wire 1 8 a $end
$var wire 1 9 b $end
$var wire 1 1 cin $end
$var wire 1 / cout $end
$var wire 1 : sum $end
$upscope $end
$scope module fa3 $end
$var wire 1 ; a $end
$var wire 1 < b $end
$var wire 1 0 cin $end
$var wire 1 * cout $end
$var wire 1 = sum $end
$upscope $end
$upscope $end
$upscope $end
$upscope $end
$enddefinitions $end
#0
$dumpvars
0=
0<
0;
0:
09
08
07
06
05
04
03
02
01
00
0/
b0 .
b0 -
b0 ,
0+
0*
b0 )
b0 (
b0 '
b0 &
0%
b0 $
b0 #
0"
b0 !
$end
#10
17
b110 !
b110 )
b110 .
1:
11
13
12
b1 $
b1 '
b1 -
b1 #
b1 &
b1 ,
#20
07
0:
1=
01
10
b1001 !
b1001 )
b1001 .
14
16
b1 (
02
15
b11 $
b11 '
b11 -
b10 #
b10 &
b10 ,
#30
1/
1=
11
10
04
07
b1000 !
b1000 )
b1000 .
0:
b110 (
12
05
18
b101 #
b101 &
b101 ,
#40
06
15
b1 $
b1 '
b1 -
b111 #
b111 &
b111 ,
#50
1"
1*
b0 !
b0 )
b0 .
0=
b1110 (
1;
b1111 #
b1111 &
b1111 ,
#60
17
1:
b1110 !
b1110 )
b1110 .
1=
b0 (
16
19
1<
b1111 $
b1111 '
b1111 -
#70
07
0:
0=
0"
01
00
0/
0*
03
06
09
0<
02
05
08
0;
b1 !
b1 )
b1 .
14
b0 $
b0 '
b0 -
b0 #
b0 &
b0 ,
1%
#80
17
b111 !
b111 )
b111 .
1:
11
13
12
b1 $
b1 '
b1 -
b1 #
b1 &
b1 ,
#90
1=
10
b1110 !
b1110 )
b1110 .
04
16
b1 (
02
15
b11 $
b11 '
b11 -
b10 #
b10 &
b10 ,
#100
1/
14
07
b1001 !
b1001 )
b1001 .
0:
b110 (
12
05
18
b101 #
b101 &
b101 ,
#110
06
15
b1 $
b1 '
b1 -
b111 #
b111 &
b111 ,
#120
1"
1*
b1 !
b1 )
b1 .
0=
b1110 (
1;
b1111 #
b1111 &
b1111 ,
#130
17
1:
b1111 !
b1111 )
b1111 .
1=
b0 (
16
19
1<
b1111 $
b1111 '
b1111 -
